README.md
setup.py
src/cioat.py
src/cioat.egg-info/PKG-INFO
src/cioat.egg-info/SOURCES.txt
src/cioat.egg-info/dependency_links.txt
src/cioat.egg-info/entry_points.txt
src/cioat.egg-info/top_level.txt