Metadata-Version: 2.1
Name: cioat
Version: 0.0.1
Summary: COVID-19's Impact on Airport Traffic
Home-page: https://github.com/jiaoyang-x/covidT
Author: JIAOYANG XU
Author-email: jiaoyangxu307@gmail.com
License: UNKNOWN
Project-URL: Bug Tracker, https://github.com/jiaoyang-x/covidT
Platform: UNKNOWN
Classifier: Programming Language :: Python :: 3
Classifier: License :: OSI Approved :: MIT License
Classifier: Operating System :: OS Independent
Requires-Python: >=3.7
